adder.v
// Adder circuit
// delay was removed when synthesized on FPGA
`define AND and #50
`define OR or #50
`define NOT not #50
`define XOR xor #50

module structuralFullAdder
(
    output sum,
    output carryout,
    input A,
    input B,
    input carryin
);
    wire AxorB;
    wire AxorBandC;
    wire AandB;

    `XOR AxorBgate(AxorB, A, B);
    `XOR AxorBxorCgate(sum, AxorB, carryin);
    `AND AandBgate(AandB,A,B);
    `AND AxorBandCgate(AxorBandC, AxorB, carryin);
    `OR  orgate(carryout, AxorBandC, AandB);

endmodule

module FullAdder4bit
(
  output[3:0] sum,  // 2's complement sum of a and b
  output carryout,  // Carry out of the summation of a and b
  output overflow,  // True if the calculation resulted in an overflow
  input[3:0] a,     // First operand in 2's complement format
  input[3:0] b      // Second operand in 2's complement format
);
    wire carry1in; // Connect carry outs to carry ins
    wire carry2in;
    wire carry3in;
    wire carryoutXor;
    wire msbXor;
    wire nmsbXor;

    structuralFullAdder adder0(sum[0],carry1in,a[0],b[0],1'b0);
    structuralFullAdder adder1(sum[1],carry2in,a[1],b[1],carry1in);
    structuralFullAdder adder2(sum[2],carry3in,a[2],b[2],carry2in);
    structuralFullAdder adder3(sum[3],carryout,a[3],b[3],carry3in);

    // An overflow has occured if the final carryout and the sum's
    // most significant bit are not the same, if you're not adding
    // a negative and positive number
    `XOR carryoutXorGate(carryoutXor,carryout,sum[3]);
    `XOR msbXorGate(msbXor, a[3], b[3]);
    `NOT nmsbXorGate(nmsbXor, msbXor);
    `AND overflowAndGate(overflow,nmsbXor,carryoutXor);
endmodule

adder.t.v
// Adder testbench
`timescale 1 ns / 1 ps
`include "adder.v"
`define DELAY 5000

module testFullAdder();
    reg[3:0] a;
    reg[3:0] b;
    wire[3:0] sum;
    wire overflow, carryout;

    FullAdder4bit adder(sum, carryout, overflow, a, b);
// We can add -8 through +7
initial begin
  $dumpfile("adder.vcd");
  $dumpvars();
  $display("Four Bit Full Adder positive + positive Tests");
  $display(" A   |  B   | Sum  | Carryout | Overflow | Sum Exp | Carryout Exp | Overflow Exp");            // Prints header for truth table
  a = 4'b0000; b = 4'b0000; #`DELAY                                 // Set A and B, wait for update (#1)
  $display("%b | %b | %b |   %b      |    %b     |  0000   | 0            | 0", a, b, sum, carryout, overflow);
  a = 4'b0001; b = 4'b0000; #`DELAY                                 // Set A and B, wait for update (#1)
  $display("%b | %b | %b |   %b      |    %b     |  0001   | 0            | 0", a, b, sum, carryout, overflow);
  a = 4'b0000; b = 4'b0001; #`DELAY                                 // Set A and B, wait for update (#1)
  $display("%b | %b | %b |   %b      |    %b     |  0001   | 0            | 0", a, b, sum, carryout, overflow);
  a = 4'b0100; b = 4'b0100; #`DELAY                                 // Set A and B, wait for update (#1)
  $display("%b | %b | %b |   %b      |    %b     |  1000   | 0            | 1", a, b, sum, carryout, overflow);
  a = 4'b0111; b = 4'b0111; #`DELAY                                 // Set A and B, wait for update (#1)
  $display("%b | %b | %b |   %b      |    %b     |  1110   | 0            | 1", a, b, sum, carryout, overflow);


  $display("\n\nFour Bit Full Adder negative + negative Tests");
  $display(" A   |  B   | Sum  | Carryout | Overflow | Sum Exp | Carryout Exp | Overflow Exp");            // Prints header for truth table
  a = 4'b1111; b = 4'b1111; #`DELAY
  $display("%b | %b | %b |   %b      |    %b     |  1110   | 1            | 0", a, b, sum, carryout, overflow);
  a = 4'b1101; b = 4'b1111; #`DELAY
  $display("%b | %b | %b |   %b      |    %b     |  1100   | 1            | 0", a, b, sum, carryout, overflow);
  a = 4'b1111; b = 4'b1101; #`DELAY
  $display("%b | %b | %b |   %b      |    %b     |  1100   | 1            | 0", a, b, sum, carryout, overflow);
  a = 4'b1001; b = 4'b1000; #`DELAY
  $display("%b | %b | %b |   %b      |    %b     |  0001   | 1            | 1", a, b, sum, carryout, overflow);
  a = 4'b1011; b = 4'b1011; #`DELAY
  $display("%b | %b | %b |   %b      |    %b     |  0110   | 1            | 1", a, b, sum, carryout, overflow);

  $display("\n\nFour Bit Full Adder negative + positive Tests");
  $display(" A   |  B   | Sum  | Carryout | Overflow | Sum Exp | Carryout Exp | Overflow Exp");            // Prints header for truth table
  a = 4'b1000; b = 4'b0001; #`DELAY
  $display("%b | %b | %b |   %b      |    %b     |  1001   | 0            | 0", a, b, sum, carryout, overflow);
  a = 4'b1001; b = 4'b0000; #`DELAY
  $display("%b | %b | %b |   %b      |    %b     |  1001   | 0            | 0", a, b, sum, carryout, overflow);
  a = 4'b1001; b = 4'b0111; #`DELAY
  $display("%b | %b | %b |   %b      |    %b     |  0000   | 1            | 0", a, b, sum, carryout, overflow);
  a = 4'b1110; b = 4'b0111; #`DELAY
  $display("%b | %b | %b |   %b      |    %b     |  0101   | 1            | 0", a, b, sum, carryout, overflow);


  $display("\n\nFour Bit Full Adder Overflow/Carryout Tests");
  $display(" A   |  B   | Sum  | Carryout | Overflow | Sum Exp | Carryout Exp | Overflow Exp");            // Prints header for truth table
  a = 4'b1001; b = 4'b1111; #`DELAY
  $display("%b | %b | %b |   %b      |    %b     |  1000   | 1            | 0", a, b, sum, carryout, overflow);
  a = 4'b1111; b = 4'b1000; #`DELAY
  $display("%b | %b | %b |   %b      |    %b     |  0111   | 1            | 1", a, b, sum, carryout, overflow);
  a = 4'b0111; b = 4'b0001; #`DELAY
  $display("%b | %b | %b |   %b      |    %b     |  1000   | 0            | 1", a, b, sum, carryout, overflow);
  a = 4'b0110; b = 4'b0001; #`DELAY
  $display("%b | %b | %b |   %b      |    %b     |  0111   | 0            | 0", a, b, sum, carryout, overflow);

end
//For hte 16 test cases, we want:
// two positive numbers added with and w/out overflow
// two negative numbers added with and w/out overflow
// A positive number added with and w/out overflow and Carryout
// There will always be overflow with positive and negative?



endmodule

adder.vcd
$date
	Wed Sep 26 19:47:33 2018
$end
$version
	Icarus Verilog
$end
$timescale
	1ps
$end
$scope module testFullAdder $end
$var wire 4 ! sum [3:0] $end
$var wire 1 " overflow $end
$var wire 1 # carryout $end
$var reg 4 $ a [3:0] $end
$var reg 4 % b [3:0] $end
$scope module adder $end
$var wire 4 & a [3:0] $end
$var wire 4 ' b [3:0] $end
$var wire 1 ( carryoutXor $end
$var wire 1 ) msbXor $end
$var wire 1 * nmsbXor $end
$var wire 1 " overflow $end
$var wire 4 + sum [3:0] $end
$var wire 1 # carryout $end
$var wire 1 , carry3in $end
$var wire 1 - carry2in $end
$var wire 1 . carry1in $end
$scope module adder0 $end
$var wire 1 / A $end
$var wire 1 0 AandB $end
$var wire 1 1 AxorB $end
$var wire 1 2 AxorBandC $end
$var wire 1 3 B $end
$var wire 1 4 carryin $end
$var wire 1 . carryout $end
$var wire 1 5 sum $end
$upscope $end
$scope module adder1 $end
$var wire 1 6 A $end
$var wire 1 7 AandB $end
$var wire 1 8 AxorB $end
$var wire 1 9 AxorBandC $end
$var wire 1 : B $end
$var wire 1 . carryin $end
$var wire 1 - carryout $end
$var wire 1 ; sum $end
$upscope $end
$scope module adder2 $end
$var wire 1 < A $end
$var wire 1 = AandB $end
$var wire 1 > AxorB $end
$var wire 1 ? AxorBandC $end
$var wire 1 @ B $end
$var wire 1 - carryin $end
$var wire 1 , carryout $end
$var wire 1 A sum $end
$upscope $end
$scope module adder3 $end
$var wire 1 B A $end
$var wire 1 C AandB $end
$var wire 1 D AxorB $end
$var wire 1 E AxorBandC $end
$var wire 1 F B $end
$var wire 1 , carryin $end
$var wire 1 # carryout $end
$var wire 1 G sum $end
$upscope $end
$upscope $end
$upscope $end
$enddefinitions $end
#0
$dumpvars
xG
0F
xE
xD
xC
0B
xA
0@
x?
x>
x=
0<
x;
0:
x9
x8
x7
06
x5
04
03
x2
x1
x0
0/
x.
x-
x,
bx +
x*
x)
x(
b0 '
b0 &
b0 %
b0 $
x#
x"
bx !
$end
#50000
01
00
08
07
0>
0=
0D
0C
0)
02
#100000
bx0 !
bx0 +
05
09
0?
0E
1*
0.
#150000
0-
0,
0#
bx00 !
bx00 +
0;
#200000
0A
b0 !
b0 +
0G
#250000
0(
#300000
0"
#5000000
1/
b1 $
b1 &
#5050000
11
#5100000
b1 !
b1 +
15
#10000000
13
0/
b1 %
b1 '
b0 $
b0 &
#15000000
03
1@
1<
b100 %
b100 '
b100 $
b100 &
#15050000
01
1=
#15100000
b0 !
b0 +
05
1,
#15150000
b1000 !
b1000 +
1G
#15200000
1(
#15250000
1"
#20000000
13
1:
1/
16
b111 %
b111 '
b111 $
b111 &
#20050000
10
17
#20100000
1.
1-
#20150000
1;
b1110 !
b1110 +
1A
#25000000
1F
1B
b1111 %
b1111 '
b1111 $
b1111 &
#25050000
1C
#25100000
1#
#25150000
0(
#25200000
0"
#30000000
06
b1101 $
b1101 &
#30050000
18
07
#30100000
b1100 !
b1100 +
0;
19
0-
#30150000
1-
b1000 !
b1000 +
0A
#30200000
b1100 !
b1100 +
1A
#35000000
0:
16
b1101 %
b1101 '
b1111 $
b1111 &
#40000000
03
0@
06
0<
b1000 %
b1000 '
b1001 $
b1001 &
#40050000
11
00
08
0=
#40100000
15
0.
b1111 !
b1111 +
1;
09
0,
#40150000
0;
0-
b101 !
b101 +
0G
#40200000
1(
b1 !
b1 +
0A
#40250000
1"
#45000000
13
1:
16
b1011 %
b1011 '
b1011 $
b1011 &
#45050000
01
10
17
#45100000
b0 !
b0 +
05
1.
1-
#45150000
1;
b110 !
b110 +
1A
#50000000
0:
0F
0/
06
b1 %
b1 '
b1000 $
b1000 &
#50050000
1D
0C
1)
11
00
07
#50100000
1G
0#
0*
b1111 !
b1111 +
15
0.
0-
#50150000
0"
0;
b1001 !
b1001 +
0A
#55000000
03
1/
b0 %
b0 '
b1001 $
b1001 &
#60000000
13
1:
1@
b111 %
b111 '
#60050000
01
10
18
1>
#60100000
05
1.
1;
b1110 !
b1110 +
1A
#60150000
b1100 !
b1100 +
0;
19
#60200000
1-
#60250000
b1000 !
b1000 +
0A
1?
#60300000
1,
#60350000
b0 !
b0 +
0G
1E
#60400000
0(
1#
#60450000
1(
#65000000
0/
16
1<
b1110 $
b1110 &
#65050000
11
00
08
17
0>
1=
#65100000
15
0.
1;
09
b111 !
b111 +
1A
0?
#65150000
b101 !
b101 +
0;
#70000000
1F
1/
06
0<
b1111 %
b1111 '
b1001 $
b1001 &
#70050000
0D
1C
0)
01
10
18
07
1>
0=
#70100000
1G
0E
1*
05
1.
1;
0-
b1010 !
b1010 +
0A
1?
0,
#70150000
0(
1"
0;
19
1A
0?
1,
b100 !
b100 +
0G
#70200000
1(
0"
1-
0,
b1100 !
b1100 +
1G
#70250000
0(
1"
0A
1?
b0 !
b0 +
0G
#70300000
1(
0"
1,
#70350000
1"
b1000 !
b1000 +
1G
#70400000
0(
#70450000
0"
#75000000
03
0:
0@
16
1<
b1000 %
b1000 '
b1111 $
b1111 &
#75050000
11
00
#75100000
b1001 !
b1001 +
15
0.
#75150000
b1011 !
b1011 +
1;
09
#75200000
0-
#75250000
b1111 !
b1111 +
1A
0?
#75300000
0,
#75350000
b111 !
b111 +
0G
#75400000
1(
#75450000
1"
#80000000
13
0F
0B
b1 %
b1 '
b111 $
b111 &
#80050000
01
10
0C
#80100000
b110 !
b110 +
05
1.
0#
#80150000
b100 !
b100 +
0;
19
0(
#80200000
1-
0"
#80250000
b0 !
b0 +
0A
1?
#80300000
1,
#80350000
b1000 !
b1000 +
1G
#80400000
1(
#80450000
1"
#85000000
0/
b110 $
b110 &
#85050000
11
00
#85100000
b1001 !
b1001 +
15
0.
#85150000
b1011 !
b1011 +
1;
09
#85200000
0-
#85250000
b1111 !
b1111 +
1A
0?
#85300000
0,
#85350000
b111 !
b111 +
0G
#85400000
0(
#85450000
0"
